MANIFEST.in
setup.cfg
setup.py
tests/__init__.py
tests/test_widget.py
tw/__init__.py
tw.openlayers.egg-info/PKG-INFO
tw.openlayers.egg-info/SOURCES.txt
tw.openlayers.egg-info/dependency_links.txt
tw.openlayers.egg-info/entry_points.txt
tw.openlayers.egg-info/namespace_packages.txt
tw.openlayers.egg-info/not-zip-safe
tw.openlayers.egg-info/paster_plugins.txt
tw.openlayers.egg-info/requires.txt
tw.openlayers.egg-info/top_level.txt
tw/openlayers/__init__.py
tw/openlayers/control.py
tw/openlayers/layer.py
tw/openlayers/map.py
tw/openlayers/release.py
tw/openlayers/samples.py
tw/openlayers/style.py
tw/openlayers/util.py
tw/openlayers/widgets.py
tw/openlayers/static/javascript/OpenLayers.js
tw/openlayers/static/javascript/OpenStreetMap.js
tw/openlayers/static/javascript/map.js
tw/openlayers/static/javascript/img/blank.gif
tw/openlayers/static/javascript/img/cloud-popup-relative.png
tw/openlayers/static/javascript/img/drag-rectangle-off.png
tw/openlayers/static/javascript/img/drag-rectangle-on.png
tw/openlayers/static/javascript/img/east-mini.png
tw/openlayers/static/javascript/img/layer-switcher-maximize.png
tw/openlayers/static/javascript/img/layer-switcher-minimize.png
tw/openlayers/static/javascript/img/marker-blue.png
tw/openlayers/static/javascript/img/marker-gold.png
tw/openlayers/static/javascript/img/marker-green.png
tw/openlayers/static/javascript/img/marker.png
tw/openlayers/static/javascript/img/measuring-stick-off.png
tw/openlayers/static/javascript/img/measuring-stick-on.png
tw/openlayers/static/javascript/img/north-mini.png
tw/openlayers/static/javascript/img/panning-hand-off.png
tw/openlayers/static/javascript/img/panning-hand-on.png
tw/openlayers/static/javascript/img/slider.png
tw/openlayers/static/javascript/img/south-mini.png
tw/openlayers/static/javascript/img/west-mini.png
tw/openlayers/static/javascript/img/zoom-minus-mini.png
tw/openlayers/static/javascript/img/zoom-plus-mini.png
tw/openlayers/static/javascript/img/zoom-world-mini.png
tw/openlayers/static/javascript/img/zoombar.png
tw/openlayers/static/javascript/theme/default/framedCloud.css
tw/openlayers/static/javascript/theme/default/style.css
tw/openlayers/static/javascript/theme/default/img/add_point_off.png
tw/openlayers/static/javascript/theme/default/img/add_point_on.png
tw/openlayers/static/javascript/theme/default/img/blank.gif
