Metadata-Version: 1.0
Name: tw.openlayers
Version: 0.8.4
Summary: ToscaWidget for OpenLayers Javascript Library
Home-page: http://toscawidgets.org, http://www.openlayers.org/
Author: Sanjiv Singh
Author-email: SinghSanjivK@gmail.com
License: UNKNOWN
Download-URL: http://toscawidgets.org/download
Keywords: toscawidgets.widgets
Platform: UNKNOWN
Classifier: Development Status :: 3 - Alpha
Classifier: Environment :: Web Environment
Classifier: Environment :: Web Environment :: ToscaWidgets
Classifier: Topic :: Software Development :: Libraries :: Python Modules
Classifier: Topic :: Software Development :: Widget Sets
Classifier: Intended Audience :: Developers
Classifier: Operating System :: OS Independent
Classifier: Programming Language :: Python
